MANIFEST.in
README.md
setup.py
streamlit_molstar/__init__.py
streamlit_molstar.egg-info/PKG-INFO
streamlit_molstar.egg-info/SOURCES.txt
streamlit_molstar.egg-info/dependency_links.txt
streamlit_molstar.egg-info/requires.txt
streamlit_molstar.egg-info/top_level.txt
streamlit_molstar/auto/__init__.py
streamlit_molstar/auto/frontend/build/asset-manifest.json
streamlit_molstar/auto/frontend/build/bootstrap.min.css
streamlit_molstar/auto/frontend/build/index.html
streamlit_molstar/auto/frontend/build/static/css/main.3b2610fa.css
streamlit_molstar/auto/frontend/build/static/css/main.3b2610fa.css.map
streamlit_molstar/auto/frontend/build/static/js/main.e04aff18.js
streamlit_molstar/auto/frontend/build/static/js/main.e04aff18.js.LICENSE.txt
streamlit_molstar/auto/frontend/build/static/js/main.e04aff18.js.map
streamlit_molstar/docking/__init__.py
streamlit_molstar/docking/frontend/build/asset-manifest.json
streamlit_molstar/docking/frontend/build/index.html
streamlit_molstar/docking/frontend/build/precache-manifest.cbe0bd1bbc61f470a31112b0e9781963.js
streamlit_molstar/docking/frontend/build/service-worker.js
streamlit_molstar/docking/frontend/build/static/css/2.42fe329c.chunk.css
streamlit_molstar/docking/frontend/build/static/css/2.42fe329c.chunk.css.map
streamlit_molstar/docking/frontend/build/static/css/main.f48d1622.chunk.css
streamlit_molstar/docking/frontend/build/static/css/main.f48d1622.chunk.css.map
streamlit_molstar/docking/frontend/build/static/js/2.92425638.chunk.js
streamlit_molstar/docking/frontend/build/static/js/2.92425638.chunk.js.LICENSE.txt
streamlit_molstar/docking/frontend/build/static/js/2.92425638.chunk.js.map
streamlit_molstar/docking/frontend/build/static/js/main.eb1a1b2d.chunk.js
streamlit_molstar/docking/frontend/build/static/js/main.eb1a1b2d.chunk.js.LICENSE.txt
streamlit_molstar/docking/frontend/build/static/js/main.eb1a1b2d.chunk.js.map
streamlit_molstar/docking/frontend/build/static/js/runtime-main.bad65001.js
streamlit_molstar/docking/frontend/build/static/js/runtime-main.bad65001.js.map
streamlit_molstar/docking/frontend/build/static/media/cells.6ace9f62.jpg
streamlit_molstar/docking/frontend/build/static/media/nebula_back6.1d38789c.jpg
