Metadata-Version: 2.1
Name: streamlit-molstar
Version: 0.4.7
Home-page: https://github.com/pragmatic-streamlit/streamlit-molstar
Author: mapix
Author-email: mapix.me@gmail.com
Classifier: Intended Audience :: Developers
Classifier: Intended Audience :: Science/Research
Classifier: Programming Language :: Python :: 3
Classifier: Programming Language :: Python :: 3.6
Classifier: Programming Language :: Python :: 3.7
Classifier: Programming Language :: Python :: 3.8
Classifier: Programming Language :: Python :: 3.9
Classifier: Programming Language :: Python :: 3.10
Classifier: License :: OSI Approved
Classifier: Topic :: Scientific/Engineering
